{
  "type": "Feature",
  "properties": {
    "iso:country":"NO",
    "sg:address":"Kristian Augusts gate 7B",
    "sg:city":"Oslo",
    "sg:classifiers":[
        {
            "category":"Professional",
            "subcategory":"Advertising",
            "type":"Services"
        }
    ],
    "sg:postcode":"0164",
    "sg:tags":[
        "3d-visualization",
        "design",
        "floor-plans",
        "interior",
        "homes",
        "decorate",
        "furniture",
        "presentation-networks",
        "community",
        "freemium",
        "premium-features",
        "property-listing"
    ],
    "sg:website":"http://www.viseno.com",
    "wof:name":"Viseno ",
    "wof:placetype":"venue"
},
  "geometry": {"coordinates":[10.685115,59.92215],"type":"Point"}
}