{
  "type": "Feature",
  "properties": {
    "iso:country":"NO",
    "sg:address":"\u00d8stensj\u00f8veien 34",
    "sg:city":"Oslo",
    "sg:classifiers":[
        {
            "category":"Professional",
            "subcategory":"Computer Services",
            "type":"Services"
        }
    ],
    "sg:postcode":"0667",
    "sg:tags":[
        "crm",
        "erp",
        "saas",
        "accounting",
        "invoice",
        "ajax",
        "email",
        "project-management"
    ],
    "sg:website":"http://24SevenOffice.com",
    "wof:name":"24SevenOffice",
    "wof:placetype":"venue"
},
  "geometry": {"coordinates":[10.812187,59.910781],"type":"Point"}
}